{"directed": true, "multigraph": true, "graph": {}, "nodes": [{"name": "1", "type": "B", "pos": [21, 70], "radius": 45, "coorX": 21, "coorY": 70, "id": "B1"}, {"name": "2", "type": "B", "pos": [17, 56], "radius": 45, "coorX": 17, "coorY": 56, "id": "B2"}, {"name": "3", "type": "B", "pos": [69, 66], "radius": 45, "coorX": 69, "coorY": 66, "id": "B3"}, {"name": "1", "type": "N", "pos": [34, 91], "radius": 25, "coorX": 34, "coorY": 91, "id": "N1"}, {"name": "2", "type": "N", "pos": [94, 43], "radius": 25, "coorX": 94, "coorY": 43, "id": "N2"}, {"name": "3", "type": "N", "pos": [34, 33], "radius": 25, "coorX": 34, "coorY": 33, "id": "N3"}, {"name": "4", "type": "N", "pos": [83, 41], "radius": 25, "coorX": 83, "coorY": 41, "id": "N4"}, {"name": "5", "type": "N", "pos": [46, 80], "radius": 25, "coorX": 46, "coorY": 80, "id": "N5"}, {"name": "6", "type": "N", "pos": [72, 77], "radius": 25, "coorX": 72, "coorY": 77, "id": "N6"}, {"name": "7", "type": "N", "pos": [74, 63], "radius": 25, "coorX": 74, "coorY": 63, "id": "N7"}, {"name": "8", "type": "N", "pos": [41, 98], "radius": 25, "coorX": 41, "coorY": 98, "id": "N8"}, {"name": "9", "type": "N", "pos": [12, 33], "radius": 25, "coorX": 12, "coorY": 33, "id": "N9"}, {"name": "10", "type": "N", "pos": [13, 53], "radius": 25, "coorX": 13, "coorY": 53, "id": "N10"}], "links": [{"type": "B_to_N", "source": "N1", "target": "B1", "key": 0}, {"type": "B_to_N", "source": "N1", "target": "B2", "key": 0}, {"type": "B_to_N", "source": "N1", "target": "B3", "key": 0}, {"type": "N_to_N", "source": "N1", "target": "N5", "key": 0}, {"type": "N_to_N", "source": "N1", "target": "N8", "key": 0}, {"type": "B_to_N", "source": "N2", "target": "B3", "key": 0}, {"type": "N_to_N", "source": "N2", "target": "N4", "key": 0}, {"type": "B_to_N", "source": "N3", "target": "B1", "key": 0}, {"type": "B_to_N", "source": "N3", "target": "B2", "key": 0}, {"type": "N_to_N", "source": "N3", "target": "N9", "key": 0}, {"type": "B_to_N", "source": "N4", "target": "B3", "key": 0}, {"type": "N_to_N", "source": "N4", "target": "N2", "key": 0}, {"type": "N_to_N", "source": "N4", "target": "N7", "key": 0}, {"type": "B_to_N", "source": "N5", "target": "B1", "key": 0}, {"type": "B_to_N", "source": "N5", "target": "B2", "key": 0}, {"type": "B_to_N", "source": "N5", "target": "B3", "key": 0}, {"type": "N_to_N", "source": "N5", "target": "N1", "key": 0}, {"type": "N_to_N", "source": "N5", "target": "N8", "key": 0}, {"type": "B_to_N", "source": "N6", "target": "B3", "key": 0}, {"type": "N_to_N", "source": "N6", "target": "N7", "key": 0}, {"type": "B_to_N", "source": "N7", "target": "B3", "key": 0}, {"type": "N_to_N", "source": "N7", "target": "N4", "key": 0}, {"type": "N_to_N", "source": "N7", "target": "N6", "key": 0}, {"type": "B_to_N", "source": "N8", "target": "B1", "key": 0}, {"type": "B_to_N", "source": "N8", "target": "B3", "key": 0}, {"type": "N_to_N", "source": "N8", "target": "N1", "key": 0}, {"type": "N_to_N", "source": "N8", "target": "N5", "key": 0}, {"type": "B_to_N", "source": "N9", "target": "B1", "key": 0}, {"type": "B_to_N", "source": "N9", "target": "B2", "key": 0}, {"type": "N_to_N", "source": "N9", "target": "N3", "key": 0}, {"type": "N_to_N", "source": "N9", "target": "N10", "key": 0}, {"type": "B_to_N", "source": "N10", "target": "B1", "key": 0}, {"type": "B_to_N", "source": "N10", "target": "B2", "key": 0}, {"type": "N_to_N", "source": "N10", "target": "N9", "key": 0}]}